PyPanorama/PyPanorama.py
PyPanorama/__init__.py
PyPanorama-0.2.dist-info/METADATA
PyPanorama-0.2.dist-info/WHEEL
PyPanorama-0.2.dist-info/top_level.txt
PyPanorama-0.2.dist-info/RECORD
