Metadata-Version: 2.1
Name: PyPanorama
Version: 0.2
Summary: A versatile Python library offering a wide range of functionalities for various applications.
Author: ZOOM
Keywords: Python,versatile,utilities,social media,Instagram,Facebook,TikTok
Requires-Python: >=3.6
